[
  {
    "sourceLang": "en",
    "targetLang": "np",
    "source": "hello",
    "target": "hello in Nigerian Pidgin"
  },
  {
    "sourceLang": "en",
    "targetLang": "ha",
    "source": "hello",
    "target": "hello in Hausa"
  },
  {
    "sourceLang": "en",
    "targetLang": "yo",
    "source": "hello",
    "target": "hello in Yoruba"
  },
  {
    "sourceLang": "en",
    "targetLang": "ig",
    "source": "hello",
    "target": "hello in Igbo"
  },
  {
    "sourceLang": "en",
    "targetLang": "fu",
    "source": "hello",
    "target": "hello in Fulfulde"
  },
  {
    "sourceLang": "en",
    "targetLang": "ka",
    "source": "hello",
    "target": "hello in Kanuri"
  },
  {
    "sourceLang": "en",
    "targetLang": "ti",
    "source": "hello",
    "target": "hello in Tiv"
  },
  {
    "sourceLang": "en",
    "targetLang": "ib",
    "source": "hello",
    "target": "hello in Ibibio"
  },
  {
    "sourceLang": "en",
    "targetLang": "ef",
    "source": "hello",
    "target": "hello in Efik"
  },
  {
    "sourceLang": "en",
    "targetLang": "ed",
    "source": "hello",
    "target": "hello in Edo"
  },
  {
    "sourceLang": "en",
    "targetLang": "nu",
    "source": "hello",
    "target": "hello in Nupe"
  },
  {
    "sourceLang": "en",
    "targetLang": "ij",
    "source": "hello",
    "target": "hello in Ijaw"
  },
  {
    "sourceLang": "en",
    "targetLang": "it",
    "source": "hello",
    "target": "hello in Itsekiri"
  },
  {
    "sourceLang": "en",
    "targetLang": "ur",
    "source": "hello",
    "target": "hello in Urhobo"
  },
  {
    "sourceLang": "en",
    "targetLang": "is",
    "source": "hello",
    "target": "hello in Isoko"
  },
  {
    "sourceLang": "en",
    "targetLang": "id",
    "source": "hello",
    "target": "hello in Idoma"
  },
  {
    "sourceLang": "en",
    "targetLang": "ga",
    "source": "hello",
    "target": "hello in Igala"
  },
  {
    "sourceLang": "en",
    "targetLang": "eb",
    "source": "hello",
    "target": "hello in Ebira"
  },
  {
    "sourceLang": "en",
    "targetLang": "gb",
    "source": "hello",
    "target": "hello in Gbagyi"
  },
  {
    "sourceLang": "en",
    "targetLang": "ju",
    "source": "hello",
    "target": "hello in Jukun"
  },
  {
    "sourceLang": "en",
    "targetLang": "bu",
    "source": "hello",
    "target": "hello in Bura"
  },
  {
    "sourceLang": "en",
    "targetLang": "ma",
    "source": "hello",
    "target": "hello in Margi"
  },
  {
    "sourceLang": "en",
    "targetLang": "mu",
    "source": "hello",
    "target": "hello in Mumuye"
  },
  {
    "sourceLang": "en",
    "targetLang": "ba",
    "source": "hello",
    "target": "hello in Bachama"
  },
  {
    "sourceLang": "en",
    "targetLang": "gw",
    "source": "hello",
    "target": "hello in Gwari"
  },
  {
    "sourceLang": "en",
    "targetLang": "ku",
    "source": "hello",
    "target": "hello in Kuteb"
  },
  {
    "sourceLang": "en",
    "targetLang": "at",
    "source": "hello",
    "target": "hello in Atyap"
  },
  {
    "sourceLang": "en",
    "targetLang": "an",
    "source": "hello",
    "target": "hello in Angas"
  },
  {
    "sourceLang": "en",
    "targetLang": "be",
    "source": "hello",
    "target": "hello in Berom"
  },
  {
    "sourceLang": "en",
    "targetLang": "eg",
    "source": "hello",
    "target": "hello in Eggon"
  },
  {
    "sourceLang": "en",
    "targetLang": "wa",
    "source": "hello",
    "target": "hello in Gwandara"
  },
  {
    "sourceLang": "en",
    "targetLang": "sa",
    "source": "hello",
    "target": "hello in Shuwa Arabic"
  },
  {
    "sourceLang": "en",
    "targetLang": "ab",
    "source": "hello",
    "target": "hello in Abanyom"
  },
  {
    "sourceLang": "en",
    "targetLang": "bo",
    "source": "hello",
    "target": "hello in Abon"
  },
  {
    "sourceLang": "en",
    "targetLang": "ua",
    "source": "hello",
    "target": "hello in Abua"
  },
  {
    "sourceLang": "en",
    "targetLang": "re",
    "source": "hello",
    "target": "hello in Abureni"
  },
  {
    "sourceLang": "en",
    "targetLang": "ae",
    "source": "hello",
    "target": "hello in Acipa Eastern"
  },
  {
    "sourceLang": "en",
    "targetLang": "aw",
    "source": "hello",
    "target": "hello in Acipa Western"
  },
  {
    "sourceLang": "en",
    "targetLang": "ad",
    "source": "hello",
    "target": "hello in Aduge"
  },
  {
    "sourceLang": "en",
    "targetLang": "af",
    "source": "hello",
    "target": "hello in Afo"
  },
  {
    "sourceLang": "en",
    "targetLang": "fa",
    "source": "hello",
    "target": "hello in Afade"
  },
  {
    "sourceLang": "en",
    "targetLang": "ah",
    "source": "hello",
    "target": "hello in Ahan"
  },
  {
    "sourceLang": "en",
    "targetLang": "aj",
    "source": "hello",
    "target": "hello in Ajawa"
  },
  {
    "sourceLang": "en",
    "targetLang": "ak",
    "source": "hello",
    "target": "hello in Akpes"
  },
  {
    "sourceLang": "en",
    "targetLang": "kw",
    "source": "hello",
    "target": "hello in Akweya-Yachi"
  },
  {
    "sourceLang": "en",
    "targetLang": "al",
    "source": "hello",
    "target": "hello in Ala"
  },
  {
    "sourceLang": "en",
    "targetLang": "la",
    "source": "hello",
    "target": "hello in Alago"
  },
  {
    "sourceLang": "en",
    "targetLang": "am",
    "source": "hello",
    "target": "hello in Amo"
  },
  {
    "sourceLang": "en",
    "targetLang": "na",
    "source": "hello",
    "target": "hello in Anaguta"
  },
  {
    "sourceLang": "en",
    "targetLang": "nd",
    "source": "hello",
    "target": "hello in Andi"
  },
  {
    "sourceLang": "en",
    "targetLang": "ny",
    "source": "hello",
    "target": "hello in Anyima"
  },
  {
    "sourceLang": "en",
    "targetLang": "ar",
    "source": "hello",
    "target": "hello in Arigidi"
  },
  {
    "sourceLang": "en",
    "targetLang": "au",
    "source": "hello",
    "target": "hello in Auyokawa"
  },
  {
    "sourceLang": "en",
    "targetLang": "ay",
    "source": "hello",
    "target": "hello in Ayere"
  },
  {
    "sourceLang": "en",
    "targetLang": "de",
    "source": "hello",
    "target": "hello in Bade"
  },
  {
    "sourceLang": "en",
    "targetLang": "bn",
    "source": "hello",
    "target": "hello in Bade North"
  },
  {
    "sourceLang": "en",
    "targetLang": "bs",
    "source": "hello",
    "target": "hello in Bade South"
  },
  {
    "sourceLang": "en",
    "targetLang": "b1",
    "source": "hello",
    "target": "hello in Baka"
  },
  {
    "sourceLang": "en",
    "targetLang": "li",
    "source": "hello",
    "target": "hello in Bali"
  },
  {
    "sourceLang": "en",
    "targetLang": "da",
    "source": "hello",
    "target": "hello in Banda"
  },
  {
    "sourceLang": "en",
    "targetLang": "as",
    "source": "hello",
    "target": "hello in Basa"
  },
  {
    "sourceLang": "en",
    "targetLang": "ag",
    "source": "hello",
    "target": "hello in Basa-Gumna"
  },
  {
    "sourceLang": "en",
    "targetLang": "ss",
    "source": "hello",
    "target": "hello in Bassa"
  },
  {
    "sourceLang": "en",
    "targetLang": "ta",
    "source": "hello",
    "target": "hello in Bata"
  },
  {
    "sourceLang": "en",
    "targetLang": "oi",
    "source": "hello",
    "target": "hello in Beboid"
  },
  {
    "sourceLang": "en",
    "targetLang": "ek",
    "source": "hello",
    "target": "hello in Bekwarra"
  },
  {
    "sourceLang": "en",
    "targetLang": "b2",
    "source": "hello",
    "target": "hello in Bena"
  },
  {
    "sourceLang": "en",
    "targetLang": "et",
    "source": "hello",
    "target": "hello in Bette"
  },
  {
    "sourceLang": "en",
    "targetLang": "bi",
    "source": "hello",
    "target": "hello in Bile"
  },
  {
    "sourceLang": "en",
    "targetLang": "in",
    "source": "hello",
    "target": "hello in Bina"
  },
  {
    "sourceLang": "en",
    "targetLang": "ni",
    "source": "hello",
    "target": "hello in Bini"
  },
  {
    "sourceLang": "en",
    "targetLang": "ol",
    "source": "hello",
    "target": "hello in Bole"
  },
  {
    "sourceLang": "en",
    "targetLang": "ok",
    "source": "hello",
    "target": "hello in Bokyi"
  },
  {
    "sourceLang": "en",
    "targetLang": "ud",
    "source": "hello",
    "target": "hello in Buduma"
  },
  {
    "sourceLang": "en",
    "targetLang": "uk",
    "source": "hello",
    "target": "hello in Bukwen"
  },
  {
    "sourceLang": "en",
    "targetLang": "ra",
    "source": "hello",
    "target": "hello in Burak"
  },
  {
    "sourceLang": "en",
    "targetLang": "ru",
    "source": "hello",
    "target": "hello in Buru"
  },
  {
    "sourceLang": "en",
    "targetLang": "bw",
    "source": "hello",
    "target": "hello in Bwatiye"
  },
  {
    "sourceLang": "en",
    "targetLang": "ch",
    "source": "hello",
    "target": "hello in Challa"
  },
  {
    "sourceLang": "en",
    "targetLang": "hi",
    "source": "hello",
    "target": "hello in Chibok"
  },
  {
    "sourceLang": "en",
    "targetLang": "hu",
    "source": "hello",
    "target": "hello in Chukkol"
  },
  {
    "sourceLang": "en",
    "targetLang": "ci",
    "source": "hello",
    "target": "hello in Cishingini"
  },
  {
    "sourceLang": "en",
    "targetLang": "di",
    "source": "hello",
    "target": "hello in Dadiya"
  },
  {
    "sourceLang": "en",
    "targetLang": "ff",
    "source": "hello",
    "target": "hello in Daffo"
  },
  {
    "sourceLang": "en",
    "targetLang": "ri",
    "source": "hello",
    "target": "hello in Dakakari"
  },
  {
    "sourceLang": "en",
    "targetLang": "d1",
    "source": "hello",
    "target": "hello in Dandi"
  },
  {
    "sourceLang": "en",
    "targetLang": "er",
    "source": "hello",
    "target": "hello in Dera"
  },
  {
    "sourceLang": "en",
    "targetLang": "iy",
    "source": "hello",
    "target": "hello in Dibiyaso"
  },
  {
    "sourceLang": "en",
    "targetLang": "d2",
    "source": "hello",
    "target": "hello in Dibo"
  },
  {
    "sourceLang": "en",
    "targetLang": "ir",
    "source": "hello",
    "target": "hello in Dirim"
  },
  {
    "sourceLang": "en",
    "targetLang": "do",
    "source": "hello",
    "target": "hello in Doka"
  },
  {
    "sourceLang": "en",
    "targetLang": "on",
    "source": "hello",
    "target": "hello in Dong"
  },
  {
    "sourceLang": "en",
    "targetLang": "du",
    "source": "hello",
    "target": "hello in Duguri"
  },
  {
    "sourceLang": "en",
    "targetLang": "uy",
    "source": "hello",
    "target": "hello in Duya"
  },
  {
    "sourceLang": "en",
    "targetLang": "ug",
    "source": "hello",
    "target": "hello in Ebughu"
  },
  {
    "sourceLang": "en",
    "targetLang": "e1",
    "source": "hello",
    "target": "hello in Ebu"
  },
  {
    "sourceLang": "en",
    "targetLang": "em",
    "source": "hello",
    "target": "hello in Emai"
  },
  {
    "sourceLang": "en",
    "targetLang": "mh",
    "source": "hello",
    "target": "hello in Emhalhe"
  },
  {
    "sourceLang": "en",
    "targetLang": "ng",
    "source": "hello",
    "target": "hello in Engenni"
  },
  {
    "sourceLang": "en",
    "targetLang": "ep",
    "source": "hello",
    "target": "hello in Epie"
  },
  {
    "sourceLang": "en",
    "targetLang": "te",
    "source": "hello",
    "target": "hello in Eten"
  },
  {
    "sourceLang": "en",
    "targetLang": "tu",
    "source": "hello",
    "target": "hello in Etung"
  },
  {
    "sourceLang": "en",
    "targetLang": "f1",
    "source": "hello",
    "target": "hello in Fali"
  },
  {
    "sourceLang": "en",
    "targetLang": "fy",
    "source": "hello",
    "target": "hello in Fyam"
  },
  {
    "sourceLang": "en",
    "targetLang": "g1",
    "source": "hello",
    "target": "hello in Gade"
  },
  {
    "sourceLang": "en",
    "targetLang": "mo",
    "source": "hello",
    "target": "hello in Gamo-Ningi"
  },
  {
    "sourceLang": "en",
    "targetLang": "wu",
    "source": "hello",
    "target": "hello in Ganawuri"
  },
  {
    "sourceLang": "en",
    "targetLang": "ge",
    "source": "hello",
    "target": "hello in Gera"
  },
  {
    "sourceLang": "en",
    "targetLang": "um",
    "source": "hello",
    "target": "hello in Geruma"
  },
  {
    "sourceLang": "en",
    "targetLang": "go",
    "source": "hello",
    "target": "hello in Gokana"
  },
  {
    "sourceLang": "en",
    "targetLang": "g2",
    "source": "hello",
    "target": "hello in Gongola"
  },
  {
    "sourceLang": "en",
    "targetLang": "nj",
    "source": "hello",
    "target": "hello in Gonja"
  },
  {
    "sourceLang": "en",
    "targetLang": "gu",
    "source": "hello",
    "target": "hello in Gude"
  },
  {
    "sourceLang": "en",
    "targetLang": "un",
    "source": "hello",
    "target": "hello in Guruntum"
  },
  {
    "sourceLang": "en",
    "targetLang": "us",
    "source": "hello",
    "target": "hello in Gusiri"
  },
  {
    "sourceLang": "en",
    "targetLang": "g3",
    "source": "hello",
    "target": "hello in Gwa"
  },
  {
    "sourceLang": "en",
    "targetLang": "gc",
    "source": "hello",
    "target": "hello in Gwari Central"
  },
  {
    "sourceLang": "en",
    "targetLang": "gn",
    "source": "hello",
    "target": "hello in Gwari North"
  },
  {
    "sourceLang": "en",
    "targetLang": "gs",
    "source": "hello",
    "target": "hello in Gwari South"
  },
  {
    "sourceLang": "en",
    "targetLang": "wo",
    "source": "hello",
    "target": "hello in Gwom"
  },
  {
    "sourceLang": "en",
    "targetLang": "oz",
    "source": "hello",
    "target": "hello in Gwoza"
  },
  {
    "sourceLang": "en",
    "targetLang": "gi",
    "source": "hello",
    "target": "hello in Higi"
  },
  {
    "sourceLang": "en",
    "targetLang": "ho",
    "source": "hello",
    "target": "hello in Holma"
  },
  {
    "sourceLang": "en",
    "targetLang": "i1",
    "source": "hello",
    "target": "hello in Ibani"
  },
  {
    "sourceLang": "en",
    "targetLang": "ic",
    "source": "hello",
    "target": "hello in Ichen"
  },
  {
    "sourceLang": "en",
    "targetLang": "i2",
    "source": "hello",
    "target": "hello in Igbira"
  },
  {
    "sourceLang": "en",
    "targetLang": "i3",
    "source": "hello",
    "target": "hello in Igede"
  },
  {
    "sourceLang": "en",
    "targetLang": "ik",
    "source": "hello",
    "target": "hello in Ika"
  },
  {
    "sourceLang": "en",
    "targetLang": "ko",
    "source": "hello",
    "target": "hello in Ikom"
  },
  {
    "sourceLang": "en",
    "targetLang": "ul",
    "source": "hello",
    "target": "hello in Ikulu"
  },
  {
    "sourceLang": "en",
    "targetLang": "we",
    "source": "hello",
    "target": "hello in Irigwe"
  },
  {
    "sourceLang": "en",
    "targetLang": "su",
    "source": "hello",
    "target": "hello in Isu"
  },
  {
    "sourceLang": "en",
    "targetLang": "iz",
    "source": "hello",
    "target": "hello in Izere"
  },
  {
    "sourceLang": "en",
    "targetLang": "ja",
    "source": "hello",
    "target": "hello in Jaba"
  },
  {
    "sourceLang": "en",
    "targetLang": "ji",
    "source": "hello",
    "target": "hello in Jibu"
  },
  {
    "sourceLang": "en",
    "targetLang": "im",
    "source": "hello",
    "target": "hello in Jimi"
  },
  {
    "sourceLang": "en",
    "targetLang": "j1",
    "source": "hello",
    "target": "hello in Jira"
  },
  {
    "sourceLang": "en",
    "targetLang": "jj",
    "source": "hello",
    "target": "hello in Jju"
  },
  {
    "sourceLang": "en",
    "targetLang": "bb",
    "source": "hello",
    "target": "hello in Kabba"
  },
  {
    "sourceLang": "en",
    "targetLang": "je",
    "source": "hello",
    "target": "hello in Kaje"
  },
  {
    "sourceLang": "en",
    "targetLang": "kn",
    "source": "hello",
    "target": "hello in Kaje North"
  },
  {
    "sourceLang": "en",
    "targetLang": "ks",
    "source": "hello",
    "target": "hello in Kaje South"
  },
  {
    "sourceLang": "en",
    "targetLang": "k1",
    "source": "hello",
    "target": "hello in Kakanda"
  },
  {
    "sourceLang": "en",
    "targetLang": "mb",
    "source": "hello",
    "target": "hello in Kambari"
  },
  {
    "sourceLang": "en",
    "targetLang": "k2",
    "source": "hello",
    "target": "hello in Kamo"
  },
  {
    "sourceLang": "en",
    "targetLang": "k3",
    "source": "hello",
    "target": "hello in Kamuku"
  },
  {
    "sourceLang": "en",
    "targetLang": "k4",
    "source": "hello",
    "target": "hello in Karekare"
  },
  {
    "sourceLang": "en",
    "targetLang": "ya",
    "source": "hello",
    "target": "hello in Kariya"
  },
  {
    "sourceLang": "en",
    "targetLang": "sh",
    "source": "hello",
    "target": "hello in Kashimawa"
  },
  {
    "sourceLang": "en",
    "targetLang": "k5",
    "source": "hello",
    "target": "hello in Katung"
  },
  {
    "sourceLang": "en",
    "targetLang": "ke",
    "source": "hello",
    "target": "hello in Kebi"
  },
  {
    "sourceLang": "en",
    "targetLang": "fi",
    "source": "hello",
    "target": "hello in Keffi"
  },
  {
    "sourceLang": "en",
    "targetLang": "kh",
    "source": "hello",
    "target": "hello in Khana"
  },
  {
    "sourceLang": "en",
    "targetLang": "ki",
    "source": "hello",
    "target": "hello in Kiballo"
  },
  {
    "sourceLang": "en",
    "targetLang": "il",
    "source": "hello",
    "target": "hello in Kilba"
  },
  {
    "sourceLang": "en",
    "targetLang": "rf",
    "source": "hello",
    "target": "hello in Kirfi"
  },
  {
    "sourceLang": "en",
    "targetLang": "om",
    "source": "hello",
    "target": "hello in Koma"
  },
  {
    "sourceLang": "en",
    "targetLang": "k6",
    "source": "hello",
    "target": "hello in Konduga"
  },
  {
    "sourceLang": "en",
    "targetLang": "or",
    "source": "hello",
    "target": "hello in Koro"
  },
  {
    "sourceLang": "en",
    "targetLang": "kp",
    "source": "hello",
    "target": "hello in Kpan"
  },
  {
    "sourceLang": "en",
    "targetLang": "lu",
    "source": "hello",
    "target": "hello in Kulung"
  },
  {
    "sourceLang": "en",
    "targetLang": "k7",
    "source": "hello",
    "target": "hello in Kurama"
  },
  {
    "sourceLang": "en",
    "targetLang": "k8",
    "source": "hello",
    "target": "hello in Kushi"
  },
  {
    "sourceLang": "en",
    "targetLang": "ut",
    "source": "hello",
    "target": "hello in Kuturmi"
  },
  {
    "sourceLang": "en",
    "targetLang": "l1",
    "source": "hello",
    "target": "hello in Lala"
  },
  {
    "sourceLang": "en",
    "targetLang": "mj",
    "source": "hello",
    "target": "hello in Lamja"
  },
  {
    "sourceLang": "en",
    "targetLang": "le",
    "source": "hello",
    "target": "hello in Lega"
  },
  {
    "sourceLang": "en",
    "targetLang": "l2",
    "source": "hello",
    "target": "hello in Lere"
  },
  {
    "sourceLang": "en",
    "targetLang": "lo",
    "source": "hello",
    "target": "hello in Loko"
  },
  {
    "sourceLang": "en",
    "targetLang": "pa",
    "source": "hello",
    "target": "hello in Lukpa"
  },
  {
    "sourceLang": "en",
    "targetLang": "aa",
    "source": "hello",
    "target": "hello in Maaka"
  },
  {
    "sourceLang": "en",
    "targetLang": "m1",
    "source": "hello",
    "target": "hello in Mada"
  },
  {
    "sourceLang": "en",
    "targetLang": "gh",
    "source": "hello",
    "target": "hello in Maghavul"
  },
  {
    "sourceLang": "en",
    "targetLang": "m2",
    "source": "hello",
    "target": "hello in Mak"
  },
  {
    "sourceLang": "en",
    "targetLang": "m3",
    "source": "hello",
    "target": "hello in Malabu"
  },
  {
    "sourceLang": "en",
    "targetLang": "lg",
    "source": "hello",
    "target": "hello in Malgwa"
  },
  {
    "sourceLang": "en",
    "targetLang": "m4",
    "source": "hello",
    "target": "hello in Mandara"
  },
  {
    "sourceLang": "en",
    "targetLang": "m5",
    "source": "hello",
    "target": "hello in Mang"
  },
  {
    "sourceLang": "en",
    "targetLang": "m6",
    "source": "hello",
    "target": "hello in Mashi"
  },
  {
    "sourceLang": "en",
    "targetLang": "m7",
    "source": "hello",
    "target": "hello in Mbat"
  },
  {
    "sourceLang": "en",
    "targetLang": "m8",
    "source": "hello",
    "target": "hello in Mbembe"
  },
  {
    "sourceLang": "en",
    "targetLang": "m9",
    "source": "hello",
    "target": "hello in Mbula"
  },
  {
    "sourceLang": "en",
    "targetLang": "ub",
    "source": "hello",
    "target": "hello in Mbube-east"
  },
  {
    "sourceLang": "en",
    "targetLang": "ew",
    "source": "hello",
    "target": "hello in Mbube-west"
  },
  {
    "sourceLang": "en",
    "targetLang": "m10",
    "source": "hello",
    "target": "hello in Mbo"
  },
  {
    "sourceLang": "en",
    "targetLang": "mi",
    "source": "hello",
    "target": "hello in Miya"
  },
  {
    "sourceLang": "en",
    "targetLang": "m11",
    "source": "hello",
    "target": "hello in Moloko"
  },
  {
    "sourceLang": "en",
    "targetLang": "nt",
    "source": "hello",
    "target": "hello in Montol"
  },
  {
    "sourceLang": "en",
    "targetLang": "ro",
    "source": "hello",
    "target": "hello in Moroa"
  },
  {
    "sourceLang": "en",
    "targetLang": "mv",
    "source": "hello",
    "target": "hello in Mvanip"
  },
  {
    "sourceLang": "en",
    "targetLang": "mw",
    "source": "hello",
    "target": "hello in Mwaghavul"
  },
  {
    "sourceLang": "en",
    "targetLang": "n1",
    "source": "hello",
    "target": "hello in Ndoro"
  },
  {
    "sourceLang": "en",
    "targetLang": "n2",
    "source": "hello",
    "target": "hello in Ngamo"
  },
  {
    "sourceLang": "en",
    "targetLang": "n3",
    "source": "hello",
    "target": "hello in Ngas"
  },
  {
    "sourceLang": "en",
    "targetLang": "zi",
    "source": "hello",
    "target": "hello in Ngizim"
  },
  {
    "sourceLang": "en",
    "targetLang": "os",
    "source": "hello",
    "target": "hello in Ngoshie"
  },
  {
    "sourceLang": "en",
    "targetLang": "n4",
    "source": "hello",
    "target": "hello in Ngwo"
  },
  {
    "sourceLang": "en",
    "targetLang": "n5",
    "source": "hello",
    "target": "hello in Njerep"
  },
  {
    "sourceLang": "en",
    "targetLang": "nk",
    "source": "hello",
    "target": "hello in Nkari"
  },
  {
    "sourceLang": "en",
    "targetLang": "n6",
    "source": "hello",
    "target": "hello in Nkim"
  },
  {
    "sourceLang": "en",
    "targetLang": "no",
    "source": "hello",
    "target": "hello in Noma"
  },
  {
    "sourceLang": "en",
    "targetLang": "n7",
    "source": "hello",
    "target": "hello in Nungu"
  },
  {
    "sourceLang": "en",
    "targetLang": "n8",
    "source": "hello",
    "target": "hello in Nyankpa"
  },
  {
    "sourceLang": "en",
    "targetLang": "ob",
    "source": "hello",
    "target": "hello in Obanliku"
  },
  {
    "sourceLang": "en",
    "targetLang": "o1",
    "source": "hello",
    "target": "hello in Obolo"
  },
  {
    "sourceLang": "en",
    "targetLang": "od",
    "source": "hello",
    "target": "hello in Odut"
  },
  {
    "sourceLang": "en",
    "targetLang": "og",
    "source": "hello",
    "target": "hello in Ogba"
  },
  {
    "sourceLang": "en",
    "targetLang": "o2",
    "source": "hello",
    "target": "hello in Ogbah"
  },
  {
    "sourceLang": "en",
    "targetLang": "ia",
    "source": "hello",
    "target": "hello in Ogbia"
  },
  {
    "sourceLang": "en",
    "targetLang": "o3",
    "source": "hello",
    "target": "hello in Ogoni"
  },
  {
    "sourceLang": "en",
    "targetLang": "kr",
    "source": "hello",
    "target": "hello in Okrika"
  },
  {
    "sourceLang": "en",
    "targetLang": "o4",
    "source": "hello",
    "target": "hello in Olulumo"
  },
  {
    "sourceLang": "en",
    "targetLang": "o5",
    "source": "hello",
    "target": "hello in Omagua"
  },
  {
    "sourceLang": "en",
    "targetLang": "o6",
    "source": "hello",
    "target": "hello in Oring"
  },
  {
    "sourceLang": "en",
    "targetLang": "o7",
    "source": "hello",
    "target": "hello in Orok"
  },
  {
    "sourceLang": "en",
    "targetLang": "o8",
    "source": "hello",
    "target": "hello in Oshimili"
  },
  {
    "sourceLang": "en",
    "targetLang": "ow",
    "source": "hello",
    "target": "hello in Owe"
  },
  {
    "sourceLang": "en",
    "targetLang": "rr",
    "source": "hello",
    "target": "hello in Owerri"
  },
  {
    "sourceLang": "en",
    "targetLang": "p1",
    "source": "hello",
    "target": "hello in Pa'a"
  },
  {
    "sourceLang": "en",
    "targetLang": "p2",
    "source": "hello",
    "target": "hello in Panyam"
  },
  {
    "sourceLang": "en",
    "targetLang": "pe",
    "source": "hello",
    "target": "hello in Pero"
  },
  {
    "sourceLang": "en",
    "targetLang": "pi",
    "source": "hello",
    "target": "hello in Piti"
  },
  {
    "sourceLang": "en",
    "targetLang": "po",
    "source": "hello",
    "target": "hello in Polci"
  },
  {
    "sourceLang": "en",
    "targetLang": "py",
    "source": "hello",
    "target": "hello in Pyem"
  },
  {
    "sourceLang": "en",
    "targetLang": "es",
    "source": "hello",
    "target": "hello in Reshe"
  },
  {
    "sourceLang": "en",
    "targetLang": "r1",
    "source": "hello",
    "target": "hello in Rogo"
  },
  {
    "sourceLang": "en",
    "targetLang": "r2",
    "source": "hello",
    "target": "hello in Ron"
  },
  {
    "sourceLang": "en",
    "targetLang": "r3",
    "source": "hello",
    "target": "hello in Rukuba"
  },
  {
    "sourceLang": "en",
    "targetLang": "s1",
    "source": "hello",
    "target": "hello in Samo"
  },
  {
    "sourceLang": "en",
    "targetLang": "s2",
    "source": "hello",
    "target": "hello in Sanga"
  },
  {
    "sourceLang": "en",
    "targetLang": "s3",
    "source": "hello",
    "target": "hello in Sankara"
  },
  {
    "sourceLang": "en",
    "targetLang": "s4",
    "source": "hello",
    "target": "hello in Shanga"
  },
  {
    "sourceLang": "en",
    "targetLang": "he",
    "source": "hello",
    "target": "hello in Sheni"
  },
  {
    "sourceLang": "en",
    "targetLang": "s5",
    "source": "hello",
    "target": "hello in Shiroro"
  },
  {
    "sourceLang": "en",
    "targetLang": "uw",
    "source": "hello",
    "target": "hello in Shuwa"
  },
  {
    "sourceLang": "en",
    "targetLang": "s6",
    "source": "hello",
    "target": "hello in Sura"
  },
  {
    "sourceLang": "en",
    "targetLang": "ne",
    "source": "hello",
    "target": "hello in Takwane"
  },
  {
    "sourceLang": "en",
    "targetLang": "t1",
    "source": "hello",
    "target": "hello in Tangale"
  },
  {
    "sourceLang": "en",
    "targetLang": "t2",
    "source": "hello",
    "target": "hello in Tarok"
  },
  {
    "sourceLang": "en",
    "targetLang": "t3",
    "source": "hello",
    "target": "hello in Tera"
  },
  {
    "sourceLang": "en",
    "targetLang": "t4",
    "source": "hello",
    "target": "hello in Teshenawa"
  },
  {
    "sourceLang": "en",
    "targetLang": "t5",
    "source": "hello",
    "target": "hello in Tita"
  },
  {
    "sourceLang": "en",
    "targetLang": "ts",
    "source": "hello",
    "target": "hello in Tsam"
  },
  {
    "sourceLang": "en",
    "targetLang": "si",
    "source": "hello",
    "target": "hello in Tsikimba"
  },
  {
    "sourceLang": "en",
    "targetLang": "t6",
    "source": "hello",
    "target": "hello in Tsishingini"
  },
  {
    "sourceLang": "en",
    "targetLang": "t7",
    "source": "hello",
    "target": "hello in Tula"
  },
  {
    "sourceLang": "en",
    "targetLang": "t8",
    "source": "hello",
    "target": "hello in Turi"
  },
  {
    "sourceLang": "en",
    "targetLang": "uf",
    "source": "hello",
    "target": "hello in Ufia"
  },
  {
    "sourceLang": "en",
    "targetLang": "el",
    "source": "hello",
    "target": "hello in Ukelle"
  },
  {
    "sourceLang": "en",
    "targetLang": "u1",
    "source": "hello",
    "target": "hello in Ukwuani"
  },
  {
    "sourceLang": "en",
    "targetLang": "me",
    "source": "hello",
    "target": "hello in Uneme"
  },
  {
    "sourceLang": "en",
    "targetLang": "u2",
    "source": "hello",
    "target": "hello in Ura"
  },
  {
    "sourceLang": "en",
    "targetLang": "to",
    "source": "hello",
    "target": "hello in Utonkon"
  },
  {
    "sourceLang": "en",
    "targetLang": "u3",
    "source": "hello",
    "target": "hello in Uwandu"
  },
  {
    "sourceLang": "en",
    "targetLang": "ve",
    "source": "hello",
    "target": "hello in Vere"
  },
  {
    "sourceLang": "en",
    "targetLang": "w1",
    "source": "hello",
    "target": "hello in Waja"
  },
  {
    "sourceLang": "en",
    "targetLang": "nn",
    "source": "hello",
    "target": "hello in Wannu"
  },
  {
    "sourceLang": "en",
    "targetLang": "rj",
    "source": "hello",
    "target": "hello in Warji"
  },
  {
    "sourceLang": "en",
    "targetLang": "rk",
    "source": "hello",
    "target": "hello in Wurkum"
  },
  {
    "sourceLang": "en",
    "targetLang": "y1",
    "source": "hello",
    "target": "hello in Yala"
  },
  {
    "sourceLang": "en",
    "targetLang": "y2",
    "source": "hello",
    "target": "hello in Yandang"
  },
  {
    "sourceLang": "en",
    "targetLang": "gk",
    "source": "hello",
    "target": "hello in Yangkam"
  },
  {
    "sourceLang": "en",
    "targetLang": "ye",
    "source": "hello",
    "target": "hello in Yergam"
  },
  {
    "sourceLang": "en",
    "targetLang": "y3",
    "source": "hello",
    "target": "hello in Yoruboid"
  },
  {
    "sourceLang": "en",
    "targetLang": "yu",
    "source": "hello",
    "target": "hello in Yungur"
  },
  {
    "sourceLang": "en",
    "targetLang": "za",
    "source": "hello",
    "target": "hello in Zaar"
  },
  {
    "sourceLang": "en",
    "targetLang": "z1",
    "source": "hello",
    "target": "hello in Zangwal"
  },
  {
    "sourceLang": "en",
    "targetLang": "rm",
    "source": "hello",
    "target": "hello in Zarma"
  },
  {
    "sourceLang": "en",
    "targetLang": "zu",
    "source": "hello",
    "target": "hello in Zul"
  },
  {
    "sourceLang": "en",
    "targetLang": "z2",
    "source": "hello",
    "target": "hello in Zumbun"
  }
]